{
  "metadata": {
    "artifact_tag": "precomps_smoke_fixture",
    "best_params": {},
    "dataset_version": "precomps_smoke_fixture",
    "feature_columns": [
      "gross_square_feet",
      "year_built",
      "building_age",
      "residential_units",
      "total_units",
      "distance_to_center_km",
      "h3_prior_sale_count",
      "h3_prior_median_price",
      "h3_prior_median_ppsf",
      "days_since_2019_start",
      "month_sin",
      "month_cos",
      "borough",
      "building_class",
      "property_segment",
      "neighborhood",
      "rate_regime_bucket"
    ],
    "feature_contract_version": "fc_v2_20260505T045612Z_b6538c8",
    "feature_drift_alerts": 16,
    "feature_drift_rows": 68,
    "feature_drift_warnings": 0,
    "feature_missingness_rows": 68,
    "local_market_features": {
      "as_of_policy": "strictly_less_than_row_sale_date",
      "feature_names": [
        "h3_prior_sale_count",
        "h3_prior_median_price",
        "h3_prior_median_ppsf"
      ],
      "min_h3_prior_count_for_h3_median": 3,
      "reference_policy": {
        "test_rows": "training split rows only; holdout targets are never used",
        "train_rows": "expanding historical rows from the training split only"
      },
      "test_missing_rates": {
        "h3_prior_median_ppsf": 0.0,
        "h3_prior_median_price": 0.0,
        "h3_prior_sale_count": 0.0
      },
      "train_missing_rates": {
        "h3_prior_median_ppsf": 0.017857142857142856,
        "h3_prior_median_price": 0.017857142857142856,
        "h3_prior_sale_count": 0.0
      }
    },
    "min_segment_rows": 2000,
    "model_package_id": "spec_nyc_avm_v2_20260505T045612Z_b6538c8",
    "model_strategy": "global",
    "model_version": "v2",
    "optuna_trials": 0,
    "pre_comps_readiness_status": "pre_comps_ready",
    "price_tier_proxy_bins_version": null,
    "router_columns": [],
    "router_mode": "segment_only",
    "sale_validity": {
      "reason_counts": {
        "etl_sqft_imputed_review": 9,
        "etl_year_built_imputed_review": 5,
        "none": 127
      },
      "status_counts": {
        "review": 13,
        "valid_training_sale": 127
      }
    },
    "segment_model_count": 0,
    "segment_ppe10_variance": 0.2857142857142857,
    "segment_variance_flag_v2": true,
    "split_manifest": {
      "all_row_ids_sha256": "a9b947ff961ff6f4f33d096cca68482af64e3a8c0c455fbb543ee63013aee231",
      "duplicate_row_ids": 0,
      "row_count": 140,
      "test_row_ids_sha256": "d147b9799c1b718981f77cf87ae7004d4e89ee14e8b6efff050f2734971fa5a3",
      "test_rows": 28,
      "train_row_ids_sha256": "c8d1a3230416ae74f7a71ed58043e47d0db9f18bdcae59bb1d491e80911e2623",
      "train_rows": 112
    },
    "target": "sale_price",
    "target_transform": "none",
    "temporal_mdape_last_minus_first": 0.0,
    "temporal_mdape_max": 0.052306767702228,
    "temporal_mdape_min": 0.052306767702228,
    "temporal_mdape_std": 0.0,
    "temporal_period_count": 1,
    "temporal_period_freq": "Q",
    "temporal_ppe10_last_minus_first": 0.0,
    "temporal_ppe10_max": 0.75,
    "temporal_ppe10_min": 0.75,
    "temporal_ppe10_std": 0.0,
    "test_rows": 28,
    "train_rows": 112,
    "trained_at_utc": "2026-05-05T04:56:17.615379"
  },
  "overall": {
    "coefficient_of_dispersion": 6.420965515519662,
    "mape": 0.06422405669358085,
    "mdape": 0.052306767702228,
    "mean_valuation_ratio": 0.9838914745964136,
    "median_valuation_ratio": 0.9764029932882123,
    "n": 28,
    "overvaluation_rate_10": 0.10714285714285714,
    "overvaluation_rate_20": 0.03571428571428571,
    "ppe10": 0.75,
    "ppe20": 0.9642857142857143,
    "ppe5": 0.42857142857142855,
    "price_related_bias": -0.5651353384565313,
    "price_related_differential": 1.008017876301086,
    "r2": 0.2971513088994283,
    "signed_pct_error_mean": -0.016108525403586652,
    "signed_pct_error_median": -0.023597006711787653,
    "undervaluation_rate_10": 0.14285714285714285,
    "undervaluation_rate_20": 0.0
  },
  "per_price_tier": {},
  "per_segment": {
    "ELEVATOR": {
      "coefficient_of_dispersion": 5.603543818716074,
      "mape": 0.05734994915137786,
      "mdape": 0.03975406162464986,
      "mean_valuation_ratio": 0.9895826453241616,
      "median_valuation_ratio": 0.9848596503695282,
      "n": 7,
      "overvaluation_rate_10": 0.14285714285714285,
      "overvaluation_rate_20": 0.0,
      "ppe10": 0.8571428571428571,
      "ppe20": 1.0,
      "ppe5": 0.5714285714285714,
      "price_related_bias": -0.5379429097387863,
      "price_related_differential": 1.006405600544237,
      "r2": 0.3762472955587005,
      "signed_pct_error_mean": -0.010417354675838405,
      "signed_pct_error_median": -0.01514034963047186,
      "undervaluation_rate_10": 0.0,
      "undervaluation_rate_20": 0.0
    },
    "SINGLE_FAMILY": {
      "coefficient_of_dispersion": 6.184013837847222,
      "mape": 0.06443703020155588,
      "mdape": 0.05088438189845475,
      "mean_valuation_ratio": 1.0022593057305393,
      "median_valuation_ratio": 0.9679463362068965,
      "n": 7,
      "overvaluation_rate_10": 0.14285714285714285,
      "overvaluation_rate_20": 0.14285714285714285,
      "ppe10": 0.8571428571428571,
      "ppe20": 0.8571428571428571,
      "ppe5": 0.42857142857142855,
      "price_related_bias": -0.632318636187532,
      "price_related_differential": 1.0083288283672678,
      "r2": 0.31244225921533075,
      "signed_pct_error_mean": 0.00225930573053938,
      "signed_pct_error_median": -0.03205366379310345,
      "undervaluation_rate_10": 0.0,
      "undervaluation_rate_20": 0.0
    },
    "SMALL_MULTI": {
      "coefficient_of_dispersion": 5.329018035200829,
      "mape": 0.05385207432024896,
      "mdape": 0.03386291018998273,
      "mean_valuation_ratio": 0.9668121679088036,
      "median_valuation_ratio": 0.9937265488018703,
      "n": 7,
      "overvaluation_rate_10": 0.0,
      "overvaluation_rate_20": 0.0,
      "ppe10": 0.7142857142857143,
      "ppe20": 1.0,
      "ppe5": 0.5714285714285714,
      "price_related_bias": -0.540401815261068,
      "price_related_differential": 1.0064711774313044,
      "r2": 0.11223237380367224,
      "signed_pct_error_mean": -0.03318783209119628,
      "signed_pct_error_median": -0.006273451198129749,
      "undervaluation_rate_10": 0.2857142857142857,
      "undervaluation_rate_20": 0.0
    },
    "WALKUP": {
      "coefficient_of_dispersion": 7.799290235074376,
      "mape": 0.0812571731011407,
      "mdape": 0.07084167750325097,
      "mean_valuation_ratio": 0.9769117794221487,
      "median_valuation_ratio": 0.9496753415300546,
      "n": 7,
      "overvaluation_rate_10": 0.14285714285714285,
      "overvaluation_rate_20": 0.0,
      "ppe10": 0.5714285714285714,
      "ppe20": 1.0,
      "ppe5": 0.14285714285714285,
      "price_related_bias": -0.5571107026183139,
      "price_related_differential": 1.0099795904110729,
      "r2": 0.30115025632077963,
      "signed_pct_error_mean": -0.023088220577851305,
      "signed_pct_error_median": -0.050324658469945355,
      "undervaluation_rate_10": 0.2857142857142857,
      "undervaluation_rate_20": 0.0
    }
  }
}